README.rst
setup.py
pyRegurgitator.egg-info/PKG-INFO
pyRegurgitator.egg-info/SOURCES.txt
pyRegurgitator.egg-info/dependency_links.txt
pyRegurgitator.egg-info/entry_points.txt
pyRegurgitator.egg-info/requires.txt
pyRegurgitator.egg-info/top_level.txt
pyreg/__init__.py
pyreg/asdlview.py
pyreg/astview.py
pyreg/py2xml.py
pyreg/asdl/changes.txt
pyreg/asdl/python25.asdl
pyreg/asdl/python25.asdl.json
pyreg/asdl/python26.asdl
pyreg/asdl/python26.asdl.json
pyreg/asdl/python27.asdl
pyreg/asdl/python27.asdl.json
pyreg/asdl/python30.asdl
pyreg/asdl/python30.asdl.json
pyreg/asdl/python31.asdl
pyreg/asdl/python31.asdl.json
pyreg/asdl/python32.asdl
pyreg/asdl/python32.asdl.json
pyreg/asdl/python33.asdl
pyreg/asdl/python33.asdl.json
pyreg/asdl/python34.asdl
pyreg/asdl/python34.asdl.json
pyreg/templates/asdl.html
pyreg/templates/ast.html
pyreg/templates/ast_node.html