Metadata-Version: 1.1
Name: pyRegurgitator
Version: 0.2.1
Summary: pyRegurgitator - Tools for analysing python code
Home-page: http://pythonhosted.org/pyRegurgitator
Author: Eduardo Naufel Schettino
Author-email: schettino72@gmail.com
License: MIT
Platform: UNKNOWN
Classifier: Development Status :: 3 - Alpha
Classifier: Environment :: Console
Classifier: Intended Audience :: Developers
Classifier: License :: OSI Approved :: MIT License
Classifier: Natural Language :: English
Classifier: Operating System :: OS Independent
Classifier: Operating System :: POSIX
Classifier: Programming Language :: Python :: 3.4
Classifier: Topic :: Software Development
